super_lio-2.0.5.dist-info/WHEEL
super_lio-2.0.5.dist-info/entry_points.txt
super_lio-2.0.5.dist-info/METADATA
super_lio-2.0.5.dist-info/RECORD
super_lio-2.0.5.dist-info/licenses/LICENSE
lib/libbasic.so
lib/liblio.so
lib/cmake/basic/basicConfig.cmake
lib/cmake/basic/basicTargets-release.cmake
lib/cmake/basic/basicTargets.cmake
super_lio/cli.py
super_lio/_super_lio_core.cpython-38-x86_64-linux-gnu.so
super_lio/config.py
super_lio/__init__.py
super_lio.libs/libsystemd-8a6eb227.so.0.23.0
super_lio.libs/libvtkRenderingFreeType-56ae2d2e.so.9.0.1
super_lio.libs/libvtkGUISupportQt-29cb0c09.so.9.0.1
super_lio.libs/libpcl_ml-77c2f5b6.so.1.11.1
super_lio.libs/libvtkInfovisCore-ca53695b.so.9.0.1
super_lio.libs/libgflags-8aee0f6c.so.2.1.2
super_lio.libs/libGLdispatch-64b28464.so.0.0.0
super_lio.libs/libvtkFiltersCore-abe23f7c.so.9.0.1
super_lio.libs/liblzma-51a76f52.so.5.2.4
super_lio.libs/libfreetype-29a7443c.so.6.16.1
super_lio.libs/libuuid-95b83d40.so.1.3.0
super_lio.libs/libvtkImagingFourier-d0383cd2.so.9.0.1
super_lio.libs/libmount-ec61bd71.so.1.1.0
super_lio.libs/libvtkFiltersHybrid-764ae8be.so.9.0.1
super_lio.libs/libtiff-70e1437f.so.5.3.0
super_lio.libs/libvtkCommonMisc-63d6a93e.so.9.0.1
super_lio.libs/libpcl_sample_consensus-6d88a963.so.1.11.1
super_lio.libs/libGLU-ff1477cc.so.1.3.1
super_lio.libs/libpcl_visualization-688a7565.so.1.11.1
super_lio.libs/libvtkImagingGeneral-91d824a4.so.9.0.1
super_lio.libs/libvtkViewsCore-904ee519.so.9.0.1
super_lio.libs/liblz4-a5753129.so.1.8.3
super_lio.libs/libicuuc-14201aad.so.60.3
super_lio.libs/libflann_cpp-357c504e.so.1.9.1
super_lio.libs/libgcrypt-a1b5cc4c.so.20.2.5
super_lio.libs/libpcl_kdtree-6b69061f.so.1.11.1
super_lio.libs/libpcl_octree-d33541ab.so.1.11.1
super_lio.libs/libvtkloguru-ee0b3af6.so.9.0.1
super_lio.libs/libvtkImagingCore-f457d8f1.so.9.0.1
super_lio.libs/libQt5Core-832803ac.so.5.15.3
super_lio.libs/libvtkInteractionImage-7b71a7c1.so.9.0.1
super_lio.libs/libboost_system-69a6c43e.so.1.66.0
super_lio.libs/libboost_filesystem-38deced9.so.1.66.0
super_lio.libs/libvtkCommonCore-e57cf74d.so.9.0.1
